LICENSE
MANIFEST.in
README.md
package.json
setup.py
thinks_dash_alert/ThinksDashAlert.py
thinks_dash_alert/__init__.py
thinks_dash_alert/_imports_.py
thinks_dash_alert/metadata.json
thinks_dash_alert/package-info.json
thinks_dash_alert/thinks_dash_alert.min.js
thinks_dash_alert/thinks_dash_alert.min.js.map
thinks_dash_alert.egg-info/PKG-INFO
thinks_dash_alert.egg-info/SOURCES.txt
thinks_dash_alert.egg-info/dependency_links.txt
thinks_dash_alert.egg-info/top_level.txt